Workbook

Sheet Coded Responses
A1: ResponseId | B1: Response | C1: Issue(s) | D1: Action(s) | E1: Site-specific | F1: Goal(s) | G1: Goal - Theme - Subtheme
A2: R_5A0ewu3YjwrNabz | B2: Safty | C2: safety | E2: 0 | F2: Other | G2: Other
A3: R_7mOSK0wrthusCAu | B3: Housing | C3: housing | E3: 0 | F3: Other | G3: Other
A4: R_64fak4VghBVFjP3 | B4: Flooding | C4: flooding | E4: 0 | F4: Informed, engaged, and responsible community | G4: Informed, engaged, and responsible community - Climate change - Resilience
A5: R_3tDm3zEsgPxc7JU | B5: Clean air | C5: air quality | E5: 0 | F5: Clean waters and sediments | G5: Clean waters and sediments - Air quality
A6: R_5hFJ0BQNvGNSACR | B6: Rising rent | C6: rent | E6: 0 | F6: Other | G6: Other
A7: R_6Jk1MgREYShQTxp | B7: Homelessness | C7: homelessness | E7: 0 | F7: Other | G7: Other
A8: R_3rUGy48x7KOH453 | B8: Mental health | C8: mental health | E8: 0 | F8: Informed, engaged, and responsible community | G8: Informed, engaged, and responsible community - Well-being - Mental health
A9: R_7r814zaMjOI8Yil | B9: Pick up trash | C9: trash | D9: clean-up | E9: 0 | F9: Clean waters and sediments | G9: Clean waters and sediments - Water quality - Trash
A10: R_5Jn1DQDgLshPm3r | B10: Afford housing | C10: housing; affordability | E10: 0 | F10: Other | G10: Other
A11: R_5jSVCublUZLV517 | B11: leave no trace | C11: habitat degradation | D11: responsible use | E11: 0 | F11: Thriving habitats and abundant wildlife; Informed, engaged, and responsible community | G11: Thriving habitats and abundant wildlife - Habitats - Habitat degradation; Informed, engaged, and responsible community - Stewardship - Accountability
A12: R_1C0Wf9Ruk3Yv3SY | B12: Build more parks | C12: park | D12: build parks | E12: 0 | F12: Informed, engaged, and responsible community | G12: Informed, engaged, and responsible community - Recreation - Availability
A13: R_3QKNoG3yhVxak7Q | B13: eliminate toxins | C13: toxins | E13: 0 | F13: Clean waters and sediments | G13: Clean waters and sediments - Water quality
A14: R_1MWB4zOOGTBiMri | B14: Mow clean streets | C14: trash; streets | E14: 0 | F14: Clean waters and sediments | G14: Clean waters and sediments - Water quality - Trash
A15: R_5PREsAyG6utdLUe | B15: Stormwater runoff | C15: stormwater runoff | E15: 0 | F15: Clean waters and sediments | G15: Clean waters and sediments - Water quality - Stormwater
A16: R_1sYI0HAxB3rfdQd | B16: Bird Saunctuaries | C16: birds | D16: wildlife santuary | E16: 0 | F16: Thriving habitats and abundant wildlife | G16: Thriving habitats and abundant wildlife - Habitats - Habitat availability; Thriving habitats and abundant wildlife - Wildlife
A17: R_5fZ5yb6ypRI5mnK | B17: Energy consumption | C17: energy consumption | E17: 0 | F17: Informed, engaged, and responsible community | G17: Informed, engaged, and responsible community - Climate change - Sustainability
A18: R_6hG5lp8hSdUe50U | B18: Policial protection | D18: political protection | E18: 0 | F18: Informed, engaged, and responsible community | G18: Informed, engaged, and responsible community - Governance - Political influence
A19: R_6kWlmNr8fxkviut | B19: stop building roads | C19: streets; development | D19: limit development | E19: 0 | F19: Thriving habitats and abundant wildlife | G19: Thriving habitats and abundant wildlife - Land use - Development
A20: R_7I4zzuoblChqYrq | B20: important to protect | E20: 0
A21: R_3UapQqWMP30w6OU | B21: the recycling program | C21: trash | D21: recycling; program | E21: 0 | F21: Clean waters and sediments | G21: Clean waters and sediments - Water quality - Trash
A22: R_5D7GOKB5ek3VrqQ | B22: Bring people together | D22: bring people together | E22: 0 | F22: Informed, engaged, and responsible community | G22: Informed, engaged, and responsible community - Engagement - Involvement
A23: R_1lPIn7GiFtRE0Jd | B23: Lealman Park clean up | C23: trash | D23: clean-up | E23: 1 | F23: Clean waters and sediments | G23: Clean waters and sediments - Water quality - Trash
A24: R_51YDtwm2RIwn2sS | B24: Cleaning up the trash | C24: trash | D24: clean-up | E24: 0 | F24: Clean waters and sediments | G24: Clean waters and sediments - Water quality - Trash
A25: R_30ZDcjMqE8nWv37 | B25: Less litter everywhere | C25: trash | E25: 0 | F25: Clean waters and sediments | G25: Clean waters and sediments - Water quality - Trash
A26: R_30PCoyttQpvvp0x | B26: Cleaner drinking water | C26: drinking water quality | E26: 0 | F26: Clean waters and sediments | G26: Clean waters and sediments - Water quality - Drinking water
A27: R_78N9F3a5biAwUSB | B27: More beach protection. | C27: beach | E27: 0 | F27: Thriving habitats and abundant wildlife | G27: Thriving habitats and abundant wildlife - Habitats
A28: R_5DOyK43u0epJA5X | B28: Crime pollution poverty | C28: crime; poverty; pollution | E28: 0 | F28: Clean waters and sediments; Other | G28: Clean waters and sediments; Other
A29: R_6k0ohglwRkMf3Mq | B29: Development has to stop | C29: development | D29: limit development | E29: 0 | F29: Thriving habitats and abundant wildlife | G29: Thriving habitats and abundant wildlife - Land use - Development
A30: R_1HHpgiNsY7rKabu | B30: Helping protect wildlife | C30: wildlife | E30: 0 | F30: Thriving habitats and abundant wildlife | G30: Thriving habitats and abundant wildlife - Wildlife
A31: R_5nBCvZcicH9EKf6 | B31: Water pollution is huge! | C31: water pollution | E31: 0 | F31: Clean waters and sediments | G31: Clean waters and sediments - Water quality
A32: R_5JW8hO2AeAkePxh | B32: Protect the environment! | E32: 0
A33: R_6nPHPnuyRqHoVgg | B33: Cleaning the environment | D33: clean-up | E33: 0 | F33: Clean waters and sediments | G33: Clean waters and sediments - Water quality - Trash
A34: R_30cNCbhCi9HmOMl | B34: Keeping trash off beaches | C34: trash; beach | E34: 0 | F34: Clean waters and sediments; Thriving habitats and abundant wildlife | G34: Clean waters and sediments - Water quality - Trash; Thriving habitats and abundant wildlife - Habitats
A35: R_7p6hJKbOdSjeHXz | B35: The air in what we breath | C35: air quality | E35: 0 | F35: Clean waters and sediments | G35: Clean waters and sediments - Air quality
A36: R_6DbHkV8gf2oX4Jq | B36: Just make places cleaner. | C36: trash | E36: 0 | F36: Clean waters and sediments | G36: Clean waters and sediments - Water quality - Trash
A37: R_5w14vdY0PQ8uGUY | B37: Water supply Redevelopment | C37: water supply; redevelopment | E37: 0 | F37: Clean waters and sediments; Thriving habitats and abundant wildlife | G37: Clean waters and sediments - Water conservation - Water supply; Thriving habitats and abundant wildlife - Land use - Development
A38: R_1kNu6ipmpGBo3SR | B38: The homeless need shelter. | C38: homelessness | D38: homeless shelter | E38: 0 | F38: Other | G38: Other
A39: R_62bePviV0kPbEfu | B39: Trash and also homenessless | C39: trash; homelessness | E39: 0 | F39: Clean waters and sediments; Other | G39: Clean waters and sediments - Water quality - Trash; Other
A40: R_7WYyLRWEuPAm9tb | B40: More rec centers and fields | D40: recreational centers; recreational fields | E40: 0 | F40: Informed, engaged, and responsible community | G40: Informed, engaged, and responsible community - Recreation - Availability
A41: R_12qMP8duMI2IiFr | B41: Crime rate needs to go down | C41: crime | E41: 0 | F41: Other | G41: Other
A42: R_71sZni4lMAt0mJx | B42: Stop building on the beach. | C42: beach; development | D42: limit development | E42: 0 | F42: Thriving habitats and abundant wildlife | G42: Thriving habitats and abundant wildlife - Land use - Development; Thriving habitats and abundant wildlife - Habitats
A43: R_5Fyc2epoW60vZco | B43: more parks and walking paths | C43: park; recreational access | D43: build parks; walking paths | E43: 0 | F43: Informed, engaged, and responsible community | G43: Informed, engaged, and responsible community - Recreation - Availability; Informed, engaged, and responsible community - Recreation - Accessibility
A44: R_31bLaPKukcaaCyV | B44: Clean the waters of our area | C44: water pollution | D44: clean-up | E44: 0 | F44: Clean waters and sediments | G44: Clean waters and sediments - Water quality
A45: R_3n0jJKMkPTKk4Nh | B45: Tampa should reduce littering | C45: trash | E45: 0 | F45: Clean waters and sediments | G45: Clean waters and sediments - Water quality - Trash
A46: R_3j7gAAcGGsa6NgY | B46: Safety of family's protection | C46: safety | E46: 0 | F46: Other | G46: Other
A47: R_5aakQiAnWIsBT2X | B47: Schools to have more education | C47: education | D47: school reform | E47: 0 | F47: Informed, engaged, and responsible community | G47: Informed, engaged, and responsible community - Engagement - Education
A48: R_5ve2me7EXPXS9X6 | B48: Traffic and grid infrastructure | C48: traffic; grid infrastructure | E48: 0 | F48: Other | G48: Other
A49: R_5yjFXFwWndiRZIc | B49: My part is cleaning up the beach | C49: trash; beach | D49: clean-up | E49: 0 | F49: Clean waters and sediments; Thriving habitats and abundant wildlife | G49: Clean waters and sediments - Water quality - Trash; Thriving habitats and abundant wildlife - Habitats
A50: R_3MLPvmFCdtylusV | B50: To have more beaches dog friendly | C50: beach; dog access | D50: policy | E50: 0 | F50: Informed, engaged, and responsible community | G50: Informed, engaged, and responsible community - Recreation - Availability
A51: R_61ajMCAfjAguxLD | B51: Cost of living, good paying jobs, | C51: cost of living; wages | E51: 0 | F51: Other | G51: Other
A52: R_5S7dRsWzER84Wnq | B52: The water and marine life quality | C52: water quality; marine life | E52: 0 | F52: Clean waters and sediments; Thriving habitats and abundant wildlife | G52: Clean waters and sediments - Water quality; Thriving habitats and abundant wildlife - Wildlife
A53: R_7S63MG1hWJVRMrG | B53: Make the prices not go up so much | C53: cost of living | E53: 0 | F53: Other | G53: Other
A54: R_5r2GbEO6X4NYWN2 | B54: More parks with attached education | C54: park; education | D54: build parks; education | E54: 0 | F54: Informed, engaged, and responsible community | G54: Informed, engaged, and responsible community - Recreation - Availability; Informed, engaged, and responsible community - Engagement - Education
A55: R_6z8DMgQApw0kqTT | B55: Keeping our beaches clean as well. | C55: trash; beach | E55: 0 | F55: Clean waters and sediments; Thriving habitats and abundant wildlife | G55: Clean waters and sediments - Water quality - Trash; Thriving habitats and abundant wildlife - Habitats
A56: R_6osWkVQBmgdgPI8 | B56: Stop so much building in our area. | C56: development | D56: limit development | E56: 0 | F56: Thriving habitats and abundant wildlife | G56: Thriving habitats and abundant wildlife - Land use - Development
A57: R_1Vf1dxZ2waC2wii | B57: clean the creeks around the bay arear | C57: creek; trash | D57: clean-up | E57: 0 | F57: Clean waters and sediments | G57: Clean waters and sediments - Water quality - Trash
A58: R_1mVF1wTKRY2CZJO | B58: Pollution and taking care of beaches. | C58: beach; pollution | E58: 0 | F58: Clean waters and sediments; Thriving habitats and abundant wildlife | G58: Clean waters and sediments - Water quality; Thriving habitats and abundant wildlife - Habitats
A59: R_60NHOstuVDcWf8l | B59: I think more affordable youth centers | C59: affordability | D59: youth centers | E59: 0 | F59: Other | G59: Other
A60: R_38JVJn9gZRsOp9L | B60: Water quality in the bay and pollution | C60: water quality; pollution | E60: 0 | F60: Clean waters and sediments | G60: Clean waters and sediments - Water quality
A61: R_7IEWEaKfFoZQWjv | B61: The amount of homelessness and poverty | C61: homelessness; poverty | E61: 0 | F61: Other | G61: Other
A62: R_62HUSuObrdnQwnf | B62: Assessment and cleaning up Rocky Creek | C62: trash; creek | D62: clean-up; assessment | E62: 1 | F62: Clean waters and sediments | G62: Clean waters and sediments - Water quality - Trash
A63: R_6ekwdir1vIZPcD1 | B63: More green space for walking or hiking. | C63: green space; recreational access | D63: build green space | E63: 0 | F63: Informed, engaged, and responsible community | G63: Informed, engaged, and responsible community - Recreation - Availability
A64: R_1vkKzVcHLfoGV3H | B64: I hope the funds are allocated properly | C64: funding allocation | E64: 0 | F64: Informed, engaged, and responsible community | G64: Informed, engaged, and responsible community - Governance - Funding
A65: R_6EbLsazwOdrtooS | B65: I liked how the image of my city improved | E65: 0
A66: R_3psS46XkXhk1avF | B66: Improve the roads, make school zones 24/7 | C66: streets; school zones | D66: policy | E66: 0 | F66: Other | G66: Other
A67: R_62tNdORBiYTMvug | B67: Economic rises, more people being homeless | C67: cost of living; homelessness | E67: 0 | F67: Other | G67: Other
A68: R_35Hi86L92JGJnhS | B68: Definitely need to improve cost of housing | C68: housing costs | E68: 0 | F68: Other | G68: Other
A69: R_6aWhuTPDN1P7ba8 | B69: Effects of using chemicals such as round up | C69: chemicals; round-up | E69: 0 | F69: Clean waters and sediments | G69: Clean waters and sediments - Water quality - Nutrients
A70: R_5yQdmVE2mGKZX1L | B70: Air quality and expansion of electric cars. | C70: air quality | D70: electric cars | E70: 0 | F70: Clean waters and sediments; Informed, engaged, and responsible community | G70: Clean waters and sediments - Air quality; Informed, engaged, and responsible community - Climate change - Sustainability
A71: R_3NadrN8a5nhVsv1 | B71: Safety for Visitors and animals of all sorts | C71: human safety; animal safety | E71: 0 | F71: Thriving habitats and abundant wildlife; Informed, engaged, and responsible community | G71: Informed, engaged, and responsible community - Well-being - Safety; Thriving habitats and abundant wildlife - Wildlife - Wildlife loss/safety
A72: R_3C15Z8J5p8y6tzK | B72: Birds and manatees are why I go to the water | C72: birds; manatees | E72: 0 | F72: Thriving habitats and abundant wildlife | G72: Thriving habitats and abundant wildlife - Wildlife
A73: R_7fLOExHaPLxAFBD | B73: Increased protection of the shallow habitats | C73: shallow habitats | E73: 0 | F73: Thriving habitats and abundant wildlife | G73: Thriving habitats and abundant wildlife - Habitats
A74: R_6YMrlwUAnBnkRvD | B74: STOP the massive overdevelopment of Florida!! | C74: overdevelopment | D74: limit development | E74: 0 | F74: Thriving habitats and abundant wildlife | G74: Thriving habitats and abundant wildlife - Land use - Development
A75: R_7y9lRqownmgkEFg | B75: KEEP OUR BEACHES CLEAN MORE FINES FOR LITTERING | C75: beach; trash | D75: fines | E75: 0 | F75: Clean waters and sediments; Thriving habitats and abundant wildlife; Informed, engaged, and responsible community | G75: Clean waters and sediments - Water quality - Trash; Thriving habitats and abundant wildlife - Habitats; Informed, engaged, and responsible community - Governance - Enforcement
A76: R_7NjYSx61pLQPoxw | B76: We need more people to go out and help wildlife | C76: wildlife | D76: civic engagement | E76: 0 | F76: Thriving habitats and abundant wildlife; Informed, engaged, and responsible community | G76: Thriving habitats and abundant wildlife - Wildlife; Informed, engaged, and responsible community - Engagement - Involvement
A77: R_5lsMRvUjhjL1zUJ | B77: Nature just in general should be tension getting | E77: 0
A78: R_1MRntJGPthxp0YP | B78: I don't like the fact we have to pay for parking | C78: parking costs | E78: 0 | F78: Other | G78: Other
A79: R_7agC2TUpgdmjIlZ | B79: I think walking accessibility could be worked on | C79: walking accessibility | E79: 0 | F79: Other | G79: Other
A80: R_11YkmIdRLEKNRHU | B80: The conservation of water is most important to me | C80: water conservation | E80: 0 | F80: Clean waters and sediments | G80: Clean waters and sediments - Water conservation
A81: R_3aS6AG6TT6LViKA | B81: Protect the wildlife that lives in these habitats | C81: wildlife | E81: 0 | F81: Thriving habitats and abundant wildlife | G81: Thriving habitats and abundant wildlife - Wildlife
A82: R_7f9MygBzT6dZaGF | B82: Trash , the killing , bullying , the mess and ect | C82: trash | E82: 0 | F82: Clean waters and sediments | G82: Clean waters and sediments - Water quality - Trash
A83: R_1DST0eCdzmmhlbX | B83: Install water softener at all homes in Tampa Bay. | C83: water softener installation | E83: 0 | F83: Clean waters and sediments | G83: Clean waters and sediments - Water quality - Drinking water
A84: R_5dPUMpTYcPsy80P | B84: Storm related concerns and habitat in lake areas. | C84: storms; lake habitat | E84: 0 | F84: Thriving habitats and abundant wildlife; Informed, engaged, and responsible community | G84: Informed, engaged, and responsible community - Climate change - Resilience; Thriving habitats and abundant wildlife - Habitats
A85: R_3EbuSSARncvO7ZJ | B85: I think people need to help out with all charities | C85: charities | D85: civic engagement | E85: 0 | F85: Other | G85: Other
A86: R_1OJVyNm6UKIZ3YE | B86: I like the state of Florida but Tampa are the best | E86: 0
A87: R_3Pk7WqDtKXLHA3g | B87: Tampa has really changed it doesn't look the same. | E87: 0
A88: R_1gwhH9n8lDOBBB3 | B88: We need to protect our waters here in Tampa General | C88: water | E88: 0 | F88: Clean waters and sediments | G88: Clean waters and sediments - Water quality
A89: R_6IJXw5OaUCJmMCK | B89: More advertising for volunteers for clean up events | C89: trash; civic engagement | D89: advertising | E89: 0 | F89: Clean waters and sediments; Informed, engaged, and responsible community | G89: Clean waters and sediments - Water quality - Trash; Informed, engaged, and responsible community - Engagement - Involvement
A90: R_31yNBoCuFEmEJJJ | B90: Make more parks and activities for small communties | C90: park; recreational access | D90: build parks; recreational activities | E90: 0 | F90: Informed, engaged, and responsible community | G90: Informed, engaged, and responsible community - Recreation - Availability
A91: R_7IzuAAviGuj0AsO | B91: Free public recreation locations for general public | C91: recreational access | D91: reduce costs | E91: 0 | F91: Informed, engaged, and responsible community | G91: Informed, engaged, and responsible community - Recreation - Accessibility
A92: R_6I7e1UJolCLxlo5 | B92: Keeping natural areas. Less development by builders. | C92: natural areas; development | D92: limit development | E92: 0 | F92: Thriving habitats and abundant wildlife | G92: Thriving habitats and abundant wildlife - Habitats - Habitat loss; Thriving habitats and abundant wildlife - Land use - Development
A93: R_84 | B93: Make drinking water in homes much purer, safer, etc. | C93: drinking water quality | E93: 0 | F93: Clean waters and sediments | G93: Clean waters and sediments - Water quality - Drinking water
A94: R_6qKIneZlNzvyzfR | B94: Water quality along with invasive non native fishes | C94: water quality; invasive species; non-native species; fish | E94: 0 | F94: Clean waters and sediments; Thriving habitats and abundant wildlife | G94: Clean waters and sediments - Water quality; Thriving habitats and abundant wildlife - Wildlife
A95: R_6joYsHNSacuuJtX | B95: STOP ALL RAW SEWAGE DUMPS INTO ANY BAY AREA WATERS!!! | C95: sewage; water quality | E95: 0 | F95: Clean waters and sediments | G95: Clean waters and sediments - Water quality - Nutrients
A96: R_3hT1g6Kw6XH9viN | B96: I would like to hear more about various volunteering. | C96: volunteering | D96: more communication | E96: 0 | F96: Informed, engaged, and responsible community | G96: Informed, engaged, and responsible community - Engagement - Involvement
A97: R_7YqNT3KFiY93QAh | B97: They should work on the pollution in the air and water | C97: air pollution; water pollution | E97: 0 | F97: Clean waters and sediments | G97: Clean waters and sediments - Air quality; Clean waters and sediments - Water quality
A98: R_5IZgX9yJ7CWWfP7 | B98: Housing inflation cost to much pollution in air control | C98: housing costs; air pollution | E98: 0 | F98: Clean waters and sediments; Other | G98: Other; Clean waters and sediments - Air quality
A99: R_5sz5UaV66xocqqB | B99: Learning how to deal with long range drought conditions | C99: drought | E99: 0 | F99: Clean waters and sediments; Informed, engaged, and responsible community | G99: Clean waters and sediments - Water conservation - Water supply; Informed, engaged, and responsible community - Climate change - Resilience
A100: R_5eqvvlM5gA9tvcQ | B100: Problem of disappearing wetlands due to new construction | C100: wetland loss; development | E100: 0 | F100: Thriving habitats and abundant wildlife | G100: Thriving habitats and abundant wildlife - Habitats - Habitat loss; Thriving habitats and abundant wildlife - Land use - Development
...

Sheet Long Format
A1: ResponseId | B1: Goal | C1: Theme | D1: Subtheme | E1: First Goal Mentioned | F1: First Theme Mentioned
A2: R_5A0ewu3YjwrNabz | B2: Other | E2: =IF(COUNTIFS($A$2:A2,A2,$B$2:B2,B2)=1,1,0) -> 1 | F2: =IF(C2="",0,IF(COUNTIFS($A$2:A2,A2,$B$2:B2,B2,$C$2:C2,C2)=1,1,0)) -> 0
A3: R_7mOSK0wrthusCAu | B3: Other | E3: =IF(COUNTIFS($A$2:A3,A3,$B$2:B3,B3)=1,1,0) -> 1 | F3: =IF(C3="",0,IF(COUNTIFS($A$2:A3,A3,$B$2:B3,B3,$C$2:C3,C3)=1,1,0)) -> 0
A4: R_64fak4VghBVFjP3 | B4: Informed, engaged, and responsible community | C4: Climate change | D4: Resilience | E4: =IF(COUNTIFS($A$2:A4,A4,$B$2:B4,B4)=1,1,0) -> 1 | F4: =IF(C4="",0,IF(COUNTIFS($A$2:A4,A4,$B$2:B4,B4,$C$2:C4,C4)=1,1,0)) -> 1
A5: R_3tDm3zEsgPxc7JU | B5: Clean waters and sediments | C5: Air quality | E5: =IF(COUNTIFS($A$2:A5,A5,$B$2:B5,B5)=1,1,0) -> 1 | F5: =IF(C5="",0,IF(COUNTIFS($A$2:A5,A5,$B$2:B5,B5,$C$2:C5,C5)=1,1,0)) -> 1
A6: R_5hFJ0BQNvGNSACR | B6: Other | E6: =IF(COUNTIFS($A$2:A6,A6,$B$2:B6,B6)=1,1,0) -> 1 | F6: =IF(C6="",0,IF(COUNTIFS($A$2:A6,A6,$B$2:B6,B6,$C$2:C6,C6)=1,1,0)) -> 0
A7: R_6Jk1MgREYShQTxp | B7: Other | E7: =IF(COUNTIFS($A$2:A7,A7,$B$2:B7,B7)=1,1,0) -> 1 | F7: =IF(C7="",0,IF(COUNTIFS($A$2:A7,A7,$B$2:B7,B7,$C$2:C7,C7)=1,1,0)) -> 0
A8: R_3rUGy48x7KOH453 | B8: Informed, engaged, and responsible community | C8: Well-being | D8: Mental health | E8: =IF(COUNTIFS($A$2:A8,A8,$B$2:B8,B8)=1,1,0) -> 1 | F8: =IF(C8="",0,IF(COUNTIFS($A$2:A8,A8,$B$2:B8,B8,$C$2:C8,C8)=1,1,0)) -> 1
A9: R_7r814zaMjOI8Yil | B9: Clean waters and sediments | C9: Water quality | D9: Trash | E9: =IF(COUNTIFS($A$2:A9,A9,$B$2:B9,B9)=1,1,0) -> 1 | F9: =IF(C9="",0,IF(COUNTIFS($A$2:A9,A9,$B$2:B9,B9,$C$2:C9,C9)=1,1,0)) -> 1
A10: R_5Jn1DQDgLshPm3r | B10: Other | E10: =IF(COUNTIFS($A$2:A10,A10,$B$2:B10,B10)=1,1,0) -> 1 | F10: =IF(C10="",0,IF(COUNTIFS($A$2:A10,A10,$B$2:B10,B10,$C$2:C10,C10)=1,1,0)) -> 0
A11: R_5jSVCublUZLV517 | B11: Thriving habitats and abundant wildlife | C11: Habitats | D11: Habitat degradation | E11: =IF(COUNTIFS($A$2:A11,A11,$B$2:B11,B11)=1,1,0) -> 1 | F11: =IF(C11="",0,IF(COUNTIFS($A$2:A11,A11,$B$2:B11,B11,$C$2:C11,C11)=1,1,0)) -> 1
A12: R_5jSVCublUZLV517 | B12: Informed, engaged, and responsible community | C12: Stewardship | D12: Accountability | E12: =IF(COUNTIFS($A$2:A12,A12,$B$2:B12,B12)=1,1,0) -> 1 | F12: =IF(C12="",0,IF(COUNTIFS($A$2:A12,A12,$B$2:B12,B12,$C$2:C12,C12)=1,1,0)) -> 1
A13: R_1C0Wf9Ruk3Yv3SY | B13: Informed, engaged, and responsible community | C13: Recreation | D13: Availability | E13: =IF(COUNTIFS($A$2:A13,A13,$B$2:B13,B13)=1,1,0) -> 1 | F13: =IF(C13="",0,IF(COUNTIFS($A$2:A13,A13,$B$2:B13,B13,$C$2:C13,C13)=1,1,0)) -> 1
A14: R_3QKNoG3yhVxak7Q | B14: Clean waters and sediments | C14: Water quality | E14: =IF(COUNTIFS($A$2:A14,A14,$B$2:B14,B14)=1,1,0) -> 1 | F14: =IF(C14="",0,IF(COUNTIFS($A$2:A14,A14,$B$2:B14,B14,$C$2:C14,C14)=1,1,0)) -> 1
A15: R_1MWB4zOOGTBiMri | B15: Clean waters and sediments | C15: Water quality | D15: Trash | E15: =IF(COUNTIFS($A$2:A15,A15,$B$2:B15,B15)=1,1,0) -> 1 | F15: =IF(C15="",0,IF(COUNTIFS($A$2:A15,A15,$B$2:B15,B15,$C$2:C15,C15)=1,1,0)) -> 1
A16: R_5PREsAyG6utdLUe | B16: Clean waters and sediments | C16: Water quality | D16: Stormwater | E16: =IF(COUNTIFS($A$2:A16,A16,$B$2:B16,B16)=1,1,0) -> 1 | F16: =IF(C16="",0,IF(COUNTIFS($A$2:A16,A16,$B$2:B16,B16,$C$2:C16,C16)=1,1,0)) -> 1
A17: R_1sYI0HAxB3rfdQd | B17: Thriving habitats and abundant wildlife | C17: Habitats | D17: Habitat availability | E17: =IF(COUNTIFS($A$2:A17,A17,$B$2:B17,B17)=1,1,0) -> 1 | F17: =IF(C17="",0,IF(COUNTIFS($A$2:A17,A17,$B$2:B17,B17,$C$2:C17,C17)=1,1,0)) -> 1
A18: R_1sYI0HAxB3rfdQd | B18: Thriving habitats and abundant wildlife | C18: Wildlife | E18: =IF(COUNTIFS($A$2:A18,A18,$B$2:B18,B18)=1,1,0) -> 0 | F18: =IF(C18="",0,IF(COUNTIFS($A$2:A18,A18,$B$2:B18,B18,$C$2:C18,C18)=1,1,0)) -> 1
A19: R_5fZ5yb6ypRI5mnK | B19: Informed, engaged, and responsible community | C19: Climate change | D19: Sustainability | E19: =IF(COUNTIFS($A$2:A19,A19,$B$2:B19,B19)=1,1,0) -> 1 | F19: =IF(C19="",0,IF(COUNTIFS($A$2:A19,A19,$B$2:B19,B19,$C$2:C19,C19)=1,1,0)) -> 1
A20: R_6hG5lp8hSdUe50U | B20: Informed, engaged, and responsible community | C20: Governance | D20: Political influence | E20: =IF(COUNTIFS($A$2:A20,A20,$B$2:B20,B20)=1,1,0) -> 1 | F20: =IF(C20="",0,IF(COUNTIFS($A$2:A20,A20,$B$2:B20,B20,$C$2:C20,C20)=1,1,0)) -> 1
A21: R_6kWlmNr8fxkviut | B21: Thriving habitats and abundant wildlife | C21: Land use | D21: Development | E21: =IF(COUNTIFS($A$2:A21,A21,$B$2:B21,B21)=1,1,0) -> 1 | F21: =IF(C21="",0,IF(COUNTIFS($A$2:A21,A21,$B$2:B21,B21,$C$2:C21,C21)=1,1,0)) -> 1
A22: R_3UapQqWMP30w6OU | B22: Clean waters and sediments | C22: Water quality | D22: Trash | E22: =IF(COUNTIFS($A$2:A22,A22,$B$2:B22,B22)=1,1,0) -> 1 | F22: =IF(C22="",0,IF(COUNTIFS($A$2:A22,A22,$B$2:B22,B22,$C$2:C22,C22)=1,1,0)) -> 1
A23: R_5D7GOKB5ek3VrqQ | B23: Informed, engaged, and responsible community | C23: Engagement | D23: Involvement | E23: =IF(COUNTIFS($A$2:A23,A23,$B$2:B23,B23)=1,1,0) -> 1 | F23: =IF(C23="",0,IF(COUNTIFS($A$2:A23,A23,$B$2:B23,B23,$C$2:C23,C23)=1,1,0)) -> 1
A24: R_1lPIn7GiFtRE0Jd | B24: Clean waters and sediments | C24: Water quality | D24: Trash | E24: =IF(COUNTIFS($A$2:A24,A24,$B$2:B24,B24)=1,1,0) -> 1 | F24: =IF(C24="",0,IF(COUNTIFS($A$2:A24,A24,$B$2:B24,B24,$C$2:C24,C24)=1,1,0)) -> 1
A25: R_51YDtwm2RIwn2sS | B25: Clean waters and sediments | C25: Water quality | D25: Trash | E25: =IF(COUNTIFS($A$2:A25,A25,$B$2:B25,B25)=1,1,0) -> 1 | F25: =IF(C25="",0,IF(COUNTIFS($A$2:A25,A25,$B$2:B25,B25,$C$2:C25,C25)=1,1,0)) -> 1
A26: R_30ZDcjMqE8nWv37 | B26: Clean waters and sediments | C26: Water quality | D26: Trash | E26: =IF(COUNTIFS($A$2:A26,A26,$B$2:B26,B26)=1,1,0) -> 1 | F26: =IF(C26="",0,IF(COUNTIFS($A$2:A26,A26,$B$2:B26,B26,$C$2:C26,C26)=1,1,0)) -> 1
A27: R_30PCoyttQpvvp0x | B27: Clean waters and sediments | C27: Water quality | D27: Drinking water | E27: =IF(COUNTIFS($A$2:A27,A27,$B$2:B27,B27)=1,1,0) -> 1 | F27: =IF(C27="",0,IF(COUNTIFS($A$2:A27,A27,$B$2:B27,B27,$C$2:C27,C27)=1,1,0)) -> 1
A28: R_78N9F3a5biAwUSB | B28: Thriving habitats and abundant wildlife | C28: Habitats | E28: =IF(COUNTIFS($A$2:A28,A28,$B$2:B28,B28)=1,1,0) -> 1 | F28: =IF(C28="",0,IF(COUNTIFS($A$2:A28,A28,$B$2:B28,B28,$C$2:C28,C28)=1,1,0)) -> 1
A29: R_5DOyK43u0epJA5X | B29: Clean waters and sediments | E29: =IF(COUNTIFS($A$2:A29,A29,$B$2:B29,B29)=1,1,0) -> 1 | F29: =IF(C29="",0,IF(COUNTIFS($A$2:A29,A29,$B$2:B29,B29,$C$2:C29,C29)=1,1,0)) -> 0
A30: R_5DOyK43u0epJA5X | B30: Other | E30: =IF(COUNTIFS($A$2:A30,A30,$B$2:B30,B30)=1,1,0) -> 1 | F30: =IF(C30="",0,IF(COUNTIFS($A$2:A30,A30,$B$2:B30,B30,$C$2:C30,C30)=1,1,0)) -> 0
A31: R_6k0ohglwRkMf3Mq | B31: Thriving habitats and abundant wildlife | C31: Land use | D31: Development | E31: =IF(COUNTIFS($A$2:A31,A31,$B$2:B31,B31)=1,1,0) -> 1 | F31: =IF(C31="",0,IF(COUNTIFS($A$2:A31,A31,$B$2:B31,B31,$C$2:C31,C31)=1,1,0)) -> 1
A32: R_1HHpgiNsY7rKabu | B32: Thriving habitats and abundant wildlife | C32: Wildlife | E32: =IF(COUNTIFS($A$2:A32,A32,$B$2:B32,B32)=1,1,0) -> 1 | F32: =IF(C32="",0,IF(COUNTIFS($A$2:A32,A32,$B$2:B32,B32,$C$2:C32,C32)=1,1,0)) -> 1
A33: R_5nBCvZcicH9EKf6 | B33: Clean waters and sediments | C33: Water quality | E33: =IF(COUNTIFS($A$2:A33,A33,$B$2:B33,B33)=1,1,0) -> 1 | F33: =IF(C33="",0,IF(COUNTIFS($A$2:A33,A33,$B$2:B33,B33,$C$2:C33,C33)=1,1,0)) -> 1
A34: R_6nPHPnuyRqHoVgg | B34: Clean waters and sediments | C34: Water quality | D34: Trash | E34: =IF(COUNTIFS($A$2:A34,A34,$B$2:B34,B34)=1,1,0) -> 1 | F34: =IF(C34="",0,IF(COUNTIFS($A$2:A34,A34,$B$2:B34,B34,$C$2:C34,C34)=1,1,0)) -> 1
A35: R_30cNCbhCi9HmOMl | B35: Clean waters and sediments | C35: Water quality | D35: Trash | E35: =IF(COUNTIFS($A$2:A35,A35,$B$2:B35,B35)=1,1,0) -> 1 | F35: =IF(C35="",0,IF(COUNTIFS($A$2:A35,A35,$B$2:B35,B35,$C$2:C35,C35)=1,1,0)) -> 1
A36: R_30cNCbhCi9HmOMl | B36: Thriving habitats and abundant wildlife | C36: Habitats | E36: =IF(COUNTIFS($A$2:A36,A36,$B$2:B36,B36)=1,1,0) -> 1 | F36: =IF(C36="",0,IF(COUNTIFS($A$2:A36,A36,$B$2:B36,B36,$C$2:C36,C36)=1,1,0)) -> 1
A37: R_7p6hJKbOdSjeHXz | B37: Clean waters and sediments | C37: Air quality | E37: =IF(COUNTIFS($A$2:A37,A37,$B$2:B37,B37)=1,1,0) -> 1 | F37: =IF(C37="",0,IF(COUNTIFS($A$2:A37,A37,$B$2:B37,B37,$C$2:C37,C37)=1,1,0)) -> 1
A38: R_6DbHkV8gf2oX4Jq | B38: Clean waters and sediments | C38: Water quality | D38: Trash | E38: =IF(COUNTIFS($A$2:A38,A38,$B$2:B38,B38)=1,1,0) -> 1 | F38: =IF(C38="",0,IF(COUNTIFS($A$2:A38,A38,$B$2:B38,B38,$C$2:C38,C38)=1,1,0)) -> 1
A39: R_5w14vdY0PQ8uGUY | B39: Clean waters and sediments | C39: Water conservation | D39: Water supply | E39: =IF(COUNTIFS($A$2:A39,A39,$B$2:B39,B39)=1,1,0) -> 1 | F39: =IF(C39="",0,IF(COUNTIFS($A$2:A39,A39,$B$2:B39,B39,$C$2:C39,C39)=1,1,0)) -> 1
A40: R_5w14vdY0PQ8uGUY | B40: Thriving habitats and abundant wildlife | C40: Land use | D40: Development | E40: =IF(COUNTIFS($A$2:A40,A40,$B$2:B40,B40)=1,1,0) -> 1 | F40: =IF(C40="",0,IF(COUNTIFS($A$2:A40,A40,$B$2:B40,B40,$C$2:C40,C40)=1,1,0)) -> 1
A41: R_1kNu6ipmpGBo3SR | B41: Other | E41: =IF(COUNTIFS($A$2:A41,A41,$B$2:B41,B41)=1,1,0) -> 1 | F41: =IF(C41="",0,IF(COUNTIFS($A$2:A41,A41,$B$2:B41,B41,$C$2:C41,C41)=1,1,0)) -> 0
A42: R_62bePviV0kPbEfu | B42: Clean waters and sediments | C42: Water quality | D42: Trash | E42: =IF(COUNTIFS($A$2:A42,A42,$B$2:B42,B42)=1,1,0) -> 1 | F42: =IF(C42="",0,IF(COUNTIFS($A$2:A42,A42,$B$2:B42,B42,$C$2:C42,C42)=1,1,0)) -> 1
A43: R_62bePviV0kPbEfu | B43: Other | E43: =IF(COUNTIFS($A$2:A43,A43,$B$2:B43,B43)=1,1,0) -> 1 | F43: =IF(C43="",0,IF(COUNTIFS($A$2:A43,A43,$B$2:B43,B43,$C$2:C43,C43)=1,1,0)) -> 0
A44: R_7WYyLRWEuPAm9tb | B44: Informed, engaged, and responsible community | C44: Recreation | D44: Availability | E44: =IF(COUNTIFS($A$2:A44,A44,$B$2:B44,B44)=1,1,0) -> 1 | F44: =IF(C44="",0,IF(COUNTIFS($A$2:A44,A44,$B$2:B44,B44,$C$2:C44,C44)=1,1,0)) -> 1
A45: R_12qMP8duMI2IiFr | B45: Other | E45: =IF(COUNTIFS($A$2:A45,A45,$B$2:B45,B45)=1,1,0) -> 1 | F45: =IF(C45="",0,IF(COUNTIFS($A$2:A45,A45,$B$2:B45,B45,$C$2:C45,C45)=1,1,0)) -> 0
A46: R_71sZni4lMAt0mJx | B46: Thriving habitats and abundant wildlife | C46: Land use | D46: Development | E46: =IF(COUNTIFS($A$2:A46,A46,$B$2:B46,B46)=1,1,0) -> 1 | F46: =IF(C46="",0,IF(COUNTIFS($A$2:A46,A46,$B$2:B46,B46,$C$2:C46,C46)=1,1,0)) -> 1
A47: R_71sZni4lMAt0mJx | B47: Thriving habitats and abundant wildlife | C47: Habitats | E47: =IF(COUNTIFS($A$2:A47,A47,$B$2:B47,B47)=1,1,0) -> 0 | F47: =IF(C47="",0,IF(COUNTIFS($A$2:A47,A47,$B$2:B47,B47,$C$2:C47,C47)=1,1,0)) -> 1
A48: R_5Fyc2epoW60vZco | B48: Informed, engaged, and responsible community | C48: Recreation | D48: Availability | E48: =IF(COUNTIFS($A$2:A48,A48,$B$2:B48,B48)=1,1,0) -> 1 | F48: =IF(C48="",0,IF(COUNTIFS($A$2:A48,A48,$B$2:B48,B48,$C$2:C48,C48)=1,1,0)) -> 1
A49: R_5Fyc2epoW60vZco | B49: Informed, engaged, and responsible community | C49: Recreation | D49: Accessibility | E49: =IF(COUNTIFS($A$2:A49,A49,$B$2:B49,B49)=1,1,0) -> 0 | F49: =IF(C49="",0,IF(COUNTIFS($A$2:A49,A49,$B$2:B49,B49,$C$2:C49,C49)=1,1,0)) -> 0
A50: R_31bLaPKukcaaCyV | B50: Clean waters and sediments | C50: Water quality | E50: =IF(COUNTIFS($A$2:A50,A50,$B$2:B50,B50)=1,1,0) -> 1 | F50: =IF(C50="",0,IF(COUNTIFS($A$2:A50,A50,$B$2:B50,B50,$C$2:C50,C50)=1,1,0)) -> 1
A51: R_3n0jJKMkPTKk4Nh | B51: Clean waters and sediments | C51: Water quality | D51: Trash | E51: =IF(COUNTIFS($A$2:A51,A51,$B$2:B51,B51)=1,1,0) -> 1 | F51: =IF(C51="",0,IF(COUNTIFS($A$2:A51,A51,$B$2:B51,B51,$C$2:C51,C51)=1,1,0)) -> 1
A52: R_3j7gAAcGGsa6NgY | B52: Other | E52: =IF(COUNTIFS($A$2:A52,A52,$B$2:B52,B52)=1,1,0) -> 1 | F52: =IF(C52="",0,IF(COUNTIFS($A$2:A52,A52,$B$2:B52,B52,$C$2:C52,C52)=1,1,0)) -> 0
A53: R_5aakQiAnWIsBT2X | B53: Informed, engaged, and responsible community | C53: Engagement | D53: Education | E53: =IF(COUNTIFS($A$2:A53,A53,$B$2:B53,B53)=1,1,0) -> 1 | F53: =IF(C53="",0,IF(COUNTIFS($A$2:A53,A53,$B$2:B53,B53,$C$2:C53,C53)=1,1,0)) -> 1
A54: R_5ve2me7EXPXS9X6 | B54: Other | E54: =IF(COUNTIFS($A$2:A54,A54,$B$2:B54,B54)=1,1,0) -> 1 | F54: =IF(C54="",0,IF(COUNTIFS($A$2:A54,A54,$B$2:B54,B54,$C$2:C54,C54)=1,1,0)) -> 0
A55: R_5yjFXFwWndiRZIc | B55: Clean waters and sediments | C55: Water quality | D55: Trash | E55: =IF(COUNTIFS($A$2:A55,A55,$B$2:B55,B55)=1,1,0) -> 1 | F55: =IF(C55="",0,IF(COUNTIFS($A$2:A55,A55,$B$2:B55,B55,$C$2:C55,C55)=1,1,0)) -> 1
A56: R_5yjFXFwWndiRZIc | B56: Thriving habitats and abundant wildlife | C56: Habitats | E56: =IF(COUNTIFS($A$2:A56,A56,$B$2:B56,B56)=1,1,0) -> 1 | F56: =IF(C56="",0,IF(COUNTIFS($A$2:A56,A56,$B$2:B56,B56,$C$2:C56,C56)=1,1,0)) -> 1
A57: R_3MLPvmFCdtylusV | B57: Informed, engaged, and responsible community | C57: Recreation | D57: Availability | E57: =IF(COUNTIFS($A$2:A57,A57,$B$2:B57,B57)=1,1,0) -> 1 | F57: =IF(C57="",0,IF(COUNTIFS($A$2:A57,A57,$B$2:B57,B57,$C$2:C57,C57)=1,1,0)) -> 1
A58: R_61ajMCAfjAguxLD | B58: Other | E58: =IF(COUNTIFS($A$2:A58,A58,$B$2:B58,B58)=1,1,0) -> 1 | F58: =IF(C58="",0,IF(COUNTIFS($A$2:A58,A58,$B$2:B58,B58,$C$2:C58,C58)=1,1,0)) -> 0
A59: R_5S7dRsWzER84Wnq | B59: Clean waters and sediments | C59: Water quality | E59: =IF(COUNTIFS($A$2:A59,A59,$B$2:B59,B59)=1,1,0) -> 1 | F59: =IF(C59="",0,IF(COUNTIFS($A$2:A59,A59,$B$2:B59,B59,$C$2:C59,C59)=1,1,0)) -> 1
A60: R_5S7dRsWzER84Wnq | B60: Thriving habitats and abundant wildlife | C60: Wildlife | E60: =IF(COUNTIFS($A$2:A60,A60,$B$2:B60,B60)=1,1,0) -> 1 | F60: =IF(C60="",0,IF(COUNTIFS($A$2:A60,A60,$B$2:B60,B60,$C$2:C60,C60)=1,1,0)) -> 1
A61: R_7S63MG1hWJVRMrG | B61: Other | E61: =IF(COUNTIFS($A$2:A61,A61,$B$2:B61,B61)=1,1,0) -> 1 | F61: =IF(C61="",0,IF(COUNTIFS($A$2:A61,A61,$B$2:B61,B61,$C$2:C61,C61)=1,1,0)) -> 0
A62: R_5r2GbEO6X4NYWN2 | B62: Informed, engaged, and responsible community | C62: Recreation | D62: Availability | E62: =IF(COUNTIFS($A$2:A62,A62,$B$2:B62,B62)=1,1,0) -> 1 | F62: =IF(C62="",0,IF(COUNTIFS($A$2:A62,A62,$B$2:B62,B62,$C$2:C62,C62)=1,1,0)) -> 1
A63: R_5r2GbEO6X4NYWN2 | B63: Informed, engaged, and responsible community | C63: Engagement | D63: Education | E63: =IF(COUNTIFS($A$2:A63,A63,$B$2:B63,B63)=1,1,0) -> 0 | F63: =IF(C63="",0,IF(COUNTIFS($A$2:A63,A63,$B$2:B63,B63,$C$2:C63,C63)=1,1,0)) -> 1
A64: R_6z8DMgQApw0kqTT | B64: Clean waters and sediments | C64: Water quality | D64: Trash | E64: =IF(COUNTIFS($A$2:A64,A64,$B$2:B64,B64)=1,1,0) -> 1 | F64: =IF(C64="",0,IF(COUNTIFS($A$2:A64,A64,$B$2:B64,B64,$C$2:C64,C64)=1,1,0)) -> 1
A65: R_6z8DMgQApw0kqTT | B65: Thriving habitats and abundant wildlife | C65: Habitats | E65: =IF(COUNTIFS($A$2:A65,A65,$B$2:B65,B65)=1,1,0) -> 1 | F65: =IF(C65="",0,IF(COUNTIFS($A$2:A65,A65,$B$2:B65,B65,$C$2:C65,C65)=1,1,0)) -> 1
A66: R_6osWkVQBmgdgPI8 | B66: Thriving habitats and abundant wildlife | C66: Land use | D66: Development | E66: =IF(COUNTIFS($A$2:A66,A66,$B$2:B66,B66)=1,1,0) -> 1 | F66: =IF(C66="",0,IF(COUNTIFS($A$2:A66,A66,$B$2:B66,B66,$C$2:C66,C66)=1,1,0)) -> 1
A67: R_1Vf1dxZ2waC2wii | B67: Clean waters and sediments | C67: Water quality | D67: Trash | E67: =IF(COUNTIFS($A$2:A67,A67,$B$2:B67,B67)=1,1,0) -> 1 | F67: =IF(C67="",0,IF(COUNTIFS($A$2:A67,A67,$B$2:B67,B67,$C$2:C67,C67)=1,1,0)) -> 1
A68: R_1mVF1wTKRY2CZJO | B68: Clean waters and sediments | C68: Water quality | E68: =IF(COUNTIFS($A$2:A68,A68,$B$2:B68,B68)=1,1,0) -> 1 | F68: =IF(C68="",0,IF(COUNTIFS($A$2:A68,A68,$B$2:B68,B68,$C$2:C68,C68)=1,1,0)) -> 1
A69: R_1mVF1wTKRY2CZJO | B69: Thriving habitats and abundant wildlife | C69: Habitats | E69: =IF(COUNTIFS($A$2:A69,A69,$B$2:B69,B69)=1,1,0) -> 1 | F69: =IF(C69="",0,IF(COUNTIFS($A$2:A69,A69,$B$2:B69,B69,$C$2:C69,C69)=1,1,0)) -> 1
A70: R_60NHOstuVDcWf8l | B70: Other | E70: =IF(COUNTIFS($A$2:A70,A70,$B$2:B70,B70)=1,1,0) -> 1 | F70: =IF(C70="",0,IF(COUNTIFS($A$2:A70,A70,$B$2:B70,B70,$C$2:C70,C70)=1,1,0)) -> 0
A71: R_38JVJn9gZRsOp9L | B71: Clean waters and sediments | C71: Water quality | E71: =IF(COUNTIFS($A$2:A71,A71,$B$2:B71,B71)=1,1,0) -> 1 | F71: =IF(C71="",0,IF(COUNTIFS($A$2:A71,A71,$B$2:B71,B71,$C$2:C71,C71)=1,1,0)) -> 1
A72: R_7IEWEaKfFoZQWjv | B72: Other | E72: =IF(COUNTIFS($A$2:A72,A72,$B$2:B72,B72)=1,1,0) -> 1 | F72: =IF(C72="",0,IF(COUNTIFS($A$2:A72,A72,$B$2:B72,B72,$C$2:C72,C72)=1,1,0)) -> 0
A73: R_62HUSuObrdnQwnf | B73: Clean waters and sediments | C73: Water quality | D73: Trash | E73: =IF(COUNTIFS($A$2:A73,A73,$B$2:B73,B73)=1,1,0) -> 1 | F73: =IF(C73="",0,IF(COUNTIFS($A$2:A73,A73,$B$2:B73,B73,$C$2:C73,C73)=1,1,0)) -> 1
A74: R_6ekwdir1vIZPcD1 | B74: Informed, engaged, and responsible community | C74: Recreation | D74: Availability | E74: =IF(COUNTIFS($A$2:A74,A74,$B$2:B74,B74)=1,1,0) -> 1 | F74: =IF(C74="",0,IF(COUNTIFS($A$2:A74,A74,$B$2:B74,B74,$C$2:C74,C74)=1,1,0)) -> 1
A75: R_1vkKzVcHLfoGV3H | B75: Informed, engaged, and responsible community | C75: Governance | D75: Funding | E75: =IF(COUNTIFS($A$2:A75,A75,$B$2:B75,B75)=1,1,0) -> 1 | F75: =IF(C75="",0,IF(COUNTIFS($A$2:A75,A75,$B$2:B75,B75,$C$2:C75,C75)=1,1,0)) -> 1
A76: R_3psS46XkXhk1avF | B76: Other | E76: =IF(COUNTIFS($A$2:A76,A76,$B$2:B76,B76)=1,1,0) -> 1 | F76: =IF(C76="",0,IF(COUNTIFS($A$2:A76,A76,$B$2:B76,B76,$C$2:C76,C76)=1,1,0)) -> 0
A77: R_62tNdORBiYTMvug | B77: Other | E77: =IF(COUNTIFS($A$2:A77,A77,$B$2:B77,B77)=1,1,0) -> 1 | F77: =IF(C77="",0,IF(COUNTIFS($A$2:A77,A77,$B$2:B77,B77,$C$2:C77,C77)=1,1,0)) -> 0
A78: R_35Hi86L92JGJnhS | B78: Other | E78: =IF(COUNTIFS($A$2:A78,A78,$B$2:B78,B78)=1,1,0) -> 1 | F78: =IF(C78="",0,IF(COUNTIFS($A$2:A78,A78,$B$2:B78,B78,$C$2:C78,C78)=1,1,0)) -> 0
A79: R_6aWhuTPDN1P7ba8 | B79: Clean waters and sediments | C79: Water quality | D79: Nutrients | E79: =IF(COUNTIFS($A$2:A79,A79,$B$2:B79,B79)=1,1,0) -> 1 | F79: =IF(C79="",0,IF(COUNTIFS($A$2:A79,A79,$B$2:B79,B79,$C$2:C79,C79)=1,1,0)) -> 1
A80: R_5yQdmVE2mGKZX1L | B80: Clean waters and sediments | C80: Air quality | E80: =IF(COUNTIFS($A$2:A80,A80,$B$2:B80,B80)=1,1,0) -> 1 | F80: =IF(C80="",0,IF(COUNTIFS($A$2:A80,A80,$B$2:B80,B80,$C$2:C80,C80)=1,1,0)) -> 1
A81: R_5yQdmVE2mGKZX1L | B81: Informed, engaged, and responsible community | C81: Climate change | D81: Sustainability | E81: =IF(COUNTIFS($A$2:A81,A81,$B$2:B81,B81)=1,1,0) -> 1 | F81: =IF(C81="",0,IF(COUNTIFS($A$2:A81,A81,$B$2:B81,B81,$C$2:C81,C81)=1,1,0)) -> 1
A82: R_3NadrN8a5nhVsv1 | B82: Informed, engaged, and responsible community | C82: Well-being | D82: Safety | E82: =IF(COUNTIFS($A$2:A82,A82,$B$2:B82,B82)=1,1,0) -> 1 | F82: =IF(C82="",0,IF(COUNTIFS($A$2:A82,A82,$B$2:B82,B82,$C$2:C82,C82)=1,1,0)) -> 1
A83: R_3NadrN8a5nhVsv1 | B83: Thriving habitats and abundant wildlife | C83: Wildlife | D83: Wildlife loss/safety | E83: =IF(COUNTIFS($A$2:A83,A83,$B$2:B83,B83)=1,1,0) -> 1 | F83: =IF(C83="",0,IF(COUNTIFS($A$2:A83,A83,$B$2:B83,B83,$C$2:C83,C83)=1,1,0)) -> 1
A84: R_3C15Z8J5p8y6tzK | B84: Thriving habitats and abundant wildlife | C84: Wildlife | E84: =IF(COUNTIFS($A$2:A84,A84,$B$2:B84,B84)=1,1,0) -> 1 | F84: =IF(C84="",0,IF(COUNTIFS($A$2:A84,A84,$B$2:B84,B84,$C$2:C84,C84)=1,1,0)) -> 1
A85: R_7fLOExHaPLxAFBD | B85: Thriving habitats and abundant wildlife | C85: Habitats | E85: =IF(COUNTIFS($A$2:A85,A85,$B$2:B85,B85)=1,1,0) -> 1 | F85: =IF(C85="",0,IF(COUNTIFS($A$2:A85,A85,$B$2:B85,B85,$C$2:C85,C85)=1,1,0)) -> 1
A86: R_6YMrlwUAnBnkRvD | B86: Thriving habitats and abundant wildlife | C86: Land use | D86: Development | E86: =IF(COUNTIFS($A$2:A86,A86,$B$2:B86,B86)=1,1,0) -> 1 | F86: =IF(C86="",0,IF(COUNTIFS($A$2:A86,A86,$B$2:B86,B86,$C$2:C86,C86)=1,1,0)) -> 1
A87: R_7y9lRqownmgkEFg | B87: Clean waters and sediments | C87: Water quality | D87: Trash | E87: =IF(COUNTIFS($A$2:A87,A87,$B$2:B87,B87)=1,1,0) -> 1 | F87: =IF(C87="",0,IF(COUNTIFS($A$2:A87,A87,$B$2:B87,B87,$C$2:C87,C87)=1,1,0)) -> 1
A88: R_7y9lRqownmgkEFg | B88: Informed, engaged, and responsible community | C88: Governance | D88: Enforcement | E88: =IF(COUNTIFS($A$2:A88,A88,$B$2:B88,B88)=1,1,0) -> 1 | F88: =IF(C88="",0,IF(COUNTIFS($A$2:A88,A88,$B$2:B88,B88,$C$2:C88,C88)=1,1,0)) -> 1
A89: R_7y9lRqownmgkEFg | B89: Thriving habitats and abundant wildlife | C89: Habitats | E89: =IF(COUNTIFS($A$2:A89,A89,$B$2:B89,B89)=1,1,0) -> 1 | F89: =IF(C89="",0,IF(COUNTIFS($A$2:A89,A89,$B$2:B89,B89,$C$2:C89,C89)=1,1,0)) -> 1
A90: R_7NjYSx61pLQPoxw | B90: Thriving habitats and abundant wildlife | C90: Wildlife | E90: =IF(COUNTIFS($A$2:A90,A90,$B$2:B90,B90)=1,1,0) -> 1 | F90: =IF(C90="",0,IF(COUNTIFS($A$2:A90,A90,$B$2:B90,B90,$C$2:C90,C90)=1,1,0)) -> 1
A91: R_7NjYSx61pLQPoxw | B91: Informed, engaged, and responsible community | C91: Engagement | D91: Involvement | E91: =IF(COUNTIFS($A$2:A91,A91,$B$2:B91,B91)=1,1,0) -> 1 | F91: =IF(C91="",0,IF(COUNTIFS($A$2:A91,A91,$B$2:B91,B91,$C$2:C91,C91)=1,1,0)) -> 1
A92: R_1MRntJGPthxp0YP | B92: Other | E92: =IF(COUNTIFS($A$2:A92,A92,$B$2:B92,B92)=1,1,0) -> 1 | F92: =IF(C92="",0,IF(COUNTIFS($A$2:A92,A92,$B$2:B92,B92,$C$2:C92,C92)=1,1,0)) -> 0
A93: R_7agC2TUpgdmjIlZ | B93: Other | E93: =IF(COUNTIFS($A$2:A93,A93,$B$2:B93,B93)=1,1,0) -> 1 | F93: =IF(C93="",0,IF(COUNTIFS($A$2:A93,A93,$B$2:B93,B93,$C$2:C93,C93)=1,1,0)) -> 0
A94: R_11YkmIdRLEKNRHU | B94: Clean waters and sediments | C94: Water conservation | E94: =IF(COUNTIFS($A$2:A94,A94,$B$2:B94,B94)=1,1,0) -> 1 | F94: =IF(C94="",0,IF(COUNTIFS($A$2:A94,A94,$B$2:B94,B94,$C$2:C94,C94)=1,1,0)) -> 1
A95: R_3aS6AG6TT6LViKA | B95: Thriving habitats and abundant wildlife | C95: Wildlife | E95: =IF(COUNTIFS($A$2:A95,A95,$B$2:B95,B95)=1,1,0) -> 1 | F95: =IF(C95="",0,IF(COUNTIFS($A$2:A95,A95,$B$2:B95,B95,$C$2:C95,C95)=1,1,0)) -> 1
A96: R_7f9MygBzT6dZaGF | B96: Clean waters and sediments | C96: Water quality | D96: Trash | E96: =IF(COUNTIFS($A$2:A96,A96,$B$2:B96,B96)=1,1,0) -> 1 | F96: =IF(C96="",0,IF(COUNTIFS($A$2:A96,A96,$B$2:B96,B96,$C$2:C96,C96)=1,1,0)) -> 1
A97: R_1DST0eCdzmmhlbX | B97: Clean waters and sediments | C97: Water quality | D97: Drinking water | E97: =IF(COUNTIFS($A$2:A97,A97,$B$2:B97,B97)=1,1,0) -> 1 | F97: =IF(C97="",0,IF(COUNTIFS($A$2:A97,A97,$B$2:B97,B97,$C$2:C97,C97)=1,1,0)) -> 1
A98: R_5dPUMpTYcPsy80P | B98: Informed, engaged, and responsible community | C98: Climate change | D98: Resilience | E98: =IF(COUNTIFS($A$2:A98,A98,$B$2:B98,B98)=1,1,0) -> 1 | F98: =IF(C98="",0,IF(COUNTIFS($A$2:A98,A98,$B$2:B98,B98,$C$2:C98,C98)=1,1,0)) -> 1
A99: R_5dPUMpTYcPsy80P | B99: Thriving habitats and abundant wildlife | C99: Habitats | E99: =IF(COUNTIFS($A$2:A99,A99,$B$2:B99,B99)=1,1,0) -> 1 | F99: =IF(C99="",0,IF(COUNTIFS($A$2:A99,A99,$B$2:B99,B99,$C$2:C99,C99)=1,1,0)) -> 1
A100: R_3EbuSSARncvO7ZJ | B100: Other | E100: =IF(COUNTIFS($A$2:A100,A100,$B$2:B100,B100)=1,1,0) -> 1 | F100: =IF(C100="",0,IF(COUNTIFS($A$2:A100,A100,$B$2:B100,B100,$C$2:C100,C100)=1,1,0)) -> 0
...

Sheet Summary
A1: Coded responses (with at least one goal) | D1: =COUNTA('Coded Responses'!F2:F335) -> 317 | J1: Responses | K1: Percent of Responses
A2: Goal | B2: Theme | C2: Subtheme | D2: Responses | E2: % of coded responses | F2: Code assignments | I2: Clean waters and sediments | J2: =D3 -> 149 | K2: =J2/$D$1*100 -> 47.003155
A3: Clean waters and sediments | D3: =SUMIFS('Long Format'!$E$2:$E$642,'Long Format'!$B$2:$B$642,A3) -> 149 | E3: =IF($D$1=0,0,D3/$D$1) -> 0.47003155 | F3: =COUNTIFS('Long Format'!$B$2:$B$642,A3) -> 184 | I3: Thriving habitats and abundant wildlife | J3: =D17 -> 139 | K3: =J3/$D$1*100 -> 43.84858
A4: Clean waters and sediments | B4: Water quality | D4: =SUMIFS('Long Format'!$F$2:$F$642,'Long Format'!$B$2:$B$642,A4,'Long Format'!$C$2:$C$642,B4) -> 128 | E4: =IF($D$1=0,0,D4/$D$1) -> 0.40378549 | F4: =COUNTIFS('Long Format'!$B$2:$B$642,A4,'Long Format'!$C$2:$C$642,B4) -> 154 | I4: Informed, engaged, and responsible community | J4: =D30 -> 140 | K4: =J4/$D$1*100 -> 44.164038
A5: Clean waters and sediments | B5: Water quality | C5: Drinking water | F5: =COUNTIFS('Long Format'!$B$2:$B$642,A5,'Long Format'!$C$2:$C$642,B5,'Long Format'!$D$2:$D$642,C5) -> 6 | I5: Other | J5: =D57 -> 42 | K5: =J5/$D$1*100 -> 13.249211
A6: Clean waters and sediments | B6: Water quality | C6: Stormwater | F6: =COUNTIFS('Long Format'!$B$2:$B$642,A6,'Long Format'!$C$2:$C$642,B6,'Long Format'!$D$2:$D$642,C6) -> 17
A7: Clean waters and sediments | B7: Water quality | C7: Nutrients | F7: =COUNTIFS('Long Format'!$B$2:$B$642,A7,'Long Format'!$C$2:$C$642,B7,'Long Format'!$D$2:$D$642,C7) -> 21 | I7: Water quality | J7: =D4 -> 128 | K7: =J7/$J$2*100 -> 85.90604
A8: Clean waters and sediments | B8: Water quality | C8: Trash | F8: =COUNTIFS('Long Format'!$B$2:$B$642,A8,'Long Format'!$C$2:$C$642,B8,'Long Format'!$D$2:$D$642,C8) -> 59 | I8: Drinking water | J8: =F5 -> 6 | K8: =J8/$J$2*100 -> 4.0268456
A9: Clean waters and sediments | B9: Water quality | C9: (none) | F9: =COUNTIFS('Long Format'!$B$2:$B$642,A9,'Long Format'!$C$2:$C$642,B9,'Long Format'!$D$2:$D$642,"") -> 51 | I9: Stormwater | J9: =F6 -> 17 | K9: =J9/$J$2*100 -> 11.409396
A10: Clean waters and sediments | B10: Water conservation | D10: =SUMIFS('Long Format'!$F$2:$F$642,'Long Format'!$B$2:$B$642,A10,'Long Format'!$C$2:$C$642,B10) -> 18 | E10: =IF($D$1=0,0,D10/$D$1) -> 0.056782334 | F10: =COUNTIFS('Long Format'!$B$2:$B$642,A10,'Long Format'!$C$2:$C$642,B10) -> 18 | I10: Nutrients | J10: =F7 -> 21 | K10: =J10/$J$2*100 -> 14.09396
A11: Clean waters and sediments | B11: Water conservation | C11: Water use | F11: =COUNTIFS('Long Format'!$B$2:$B$642,A11,'Long Format'!$C$2:$C$642,B11,'Long Format'!$D$2:$D$642,C11) -> 7 | I11: Trash | J11: =F8 -> 59 | K11: =J11/$J$2*100 -> 39.597315
A12: Clean waters and sediments | B12: Water conservation | C12: Water supply | F12: =COUNTIFS('Long Format'!$B$2:$B$642,A12,'Long Format'!$C$2:$C$642,B12,'Long Format'!$D$2:$D$642,C12) -> 10 | I12: Water conservation | J12: =D10 -> 18 | K12: =J12/$J$2*100 -> 12.080537
A13: Clean waters and sediments | B13: Water conservation | C13: (none) | F13: =COUNTIFS('Long Format'!$B$2:$B$642,A13,'Long Format'!$C$2:$C$642,B13,'Long Format'!$D$2:$D$642,"") -> 1 | I13: Water use | J13: =F11 -> 7 | K13: =J13/$J$2*100 -> 4.6979866
A14: Clean waters and sediments | B14: Air quality | D14: =SUMIFS('Long Format'!$F$2:$F$642,'Long Format'!$B$2:$B$642,A14,'Long Format'!$C$2:$C$642,B14) -> 9 | E14: =IF($D$1=0,0,D14/$D$1) -> 0.028391167 | F14: =COUNTIFS('Long Format'!$B$2:$B$642,A14,'Long Format'!$C$2:$C$642,B14) -> 9 | I14: Water supply | J14: =F12 -> 10 | K14: =J14/$J$2*100 -> 6.7114094
A15: Clean waters and sediments | B15: Air quality | C15: (none) | F15: =COUNTIFS('Long Format'!$B$2:$B$642,A15,'Long Format'!$C$2:$C$642,B15,'Long Format'!$D$2:$D$642,"") -> 9 | I15: Air quality | J15: =D14 -> 9 | K15: =J15/$J$2*100 -> 6.0402685
A16: Clean waters and sediments | F16: =COUNTIFS('Long Format'!$B$2:$B$642,A16,'Long Format'!$C$2:$C$642,"") -> 3
A17: Thriving habitats and abundant wildlife | D17: =SUMIFS('Long Format'!$E$2:$E$642,'Long Format'!$B$2:$B$642,A17) -> 139 | E17: =IF($D$1=0,0,D17/$D$1) -> 0.4384858 | F17: =COUNTIFS('Long Format'!$B$2:$B$642,A17) -> 224
A18: Thriving habitats and abundant wildlife | B18: Habitats | D18: =SUMIFS('Long Format'!$F$2:$F$642,'Long Format'!$B$2:$B$642,A18,'Long Format'!$C$2:$C$642,B18) -> 84 | E18: =IF($D$1=0,0,D18/$D$1) -> 0.26498423 | F18: =COUNTIFS('Long Format'!$B$2:$B$642,A18,'Long Format'!$C$2:$C$642,B18) -> 94
A19: Thriving habitats and abundant wildlife | B19: Habitats | C19: Habitat degradation | F19: =COUNTIFS('Long Format'!$B$2:$B$642,A19,'Long Format'!$C$2:$C$642,B19,'Long Format'!$D$2:$D$642,C19) -> 28 | I19: Habitats | J19: =D18 -> 84 | K19: =J19/$J$3*100 -> 60.431655
A20: Thriving habitats and abundant wildlife | B20: Habitats | C20: Habitat loss | F20: =COUNTIFS('Long Format'!$B$2:$B$642,A20,'Long Format'!$C$2:$C$642,B20,'Long Format'!$D$2:$D$642,C20) -> 30 | I20: Habitat degradation | J20: =F19 -> 28 | K20: =J20/$J$3*100 -> 20.143885
A21: Thriving habitats and abundant wildlife | B21: Habitats | C21: Habitat availability | F21: =COUNTIFS('Long Format'!$B$2:$B$642,A21,'Long Format'!$C$2:$C$642,B21,'Long Format'!$D$2:$D$642,C21) -> 17 | I21: Habitat loss | J21: =F20 -> 30 | K21: =J21/$J$3*100 -> 21.582734
A22: Thriving habitats and abundant wildlife | B22: Habitats | C22: (none) | F22: =COUNTIFS('Long Format'!$B$2:$B$642,A22,'Long Format'!$C$2:$C$642,B22,'Long Format'!$D$2:$D$642,"") -> 19 | I22: Habitat availability | J22: =F21 -> 17 | K22: =J22/$J$3*100 -> 12.230216
A23: Thriving habitats and abundant wildlife | B23: Wildlife | D23: =SUMIFS('Long Format'!$F$2:$F$642,'Long Format'!$B$2:$B$642,A23,'Long Format'!$C$2:$C$642,B23) -> 75 | E23: =IF($D$1=0,0,D23/$D$1) -> 0.23659306 | F23: =COUNTIFS('Long Format'!$B$2:$B$642,A23,'Long Format'!$C$2:$C$642,B23) -> 77 | I23: Wildlife | J23: =D23 -> 75 | K23: =J23/$J$3*100 -> 53.956835
A24: Thriving habitats and abundant wildlife | B24: Wildlife | C24: Wildlife loss/safety | F24: =COUNTIFS('Long Format'!$B$2:$B$642,A24,'Long Format'!$C$2:$C$642,B24,'Long Format'!$D$2:$D$642,C24) -> 25 | I24: Wildlife loss/safety | J24: =F24 -> 25 | K24: =J24/$J$3*100 -> 17.985612
A25: Thriving habitats and abundant wildlife | B25: Wildlife | C25: Wildlife displacement | F25: =COUNTIFS('Long Format'!$B$2:$B$642,A25,'Long Format'!$C$2:$C$642,B25,'Long Format'!$D$2:$D$642,C25) -> 9 | I25: Wildlife displacement | J25: =F25 -> 9 | K25: =J25/$J$3*100 -> 6.4748201
A26: Thriving habitats and abundant wildlife | B26: Wildlife | C26: (none) | F26: =COUNTIFS('Long Format'!$B$2:$B$642,A26,'Long Format'!$C$2:$C$642,B26,'Long Format'!$D$2:$D$642,"") -> 43 | I26: Land use | J26: =D27 -> 53 | K26: =J26/$J$3*100 -> 38.129496
A27: Thriving habitats and abundant wildlife | B27: Land use | D27: =SUMIFS('Long Format'!$F$2:$F$642,'Long Format'!$B$2:$B$642,A27,'Long Format'!$C$2:$C$642,B27) -> 53 | E27: =IF($D$1=0,0,D27/$D$1) -> 0.16719243 | F27: =COUNTIFS('Long Format'!$B$2:$B$642,A27,'Long Format'!$C$2:$C$642,B27) -> 53 | I27: Development | J27: =F28 -> 52 | K27: =J27/$J$3*100 -> 37.410072
A28: Thriving habitats and abundant wildlife | B28: Land use | C28: Development | F28: =COUNTIFS('Long Format'!$B$2:$B$642,A28,'Long Format'!$C$2:$C$642,B28,'Long Format'!$D$2:$D$642,C28) -> 52
A29: Thriving habitats and abundant wildlife | B29: Land use | C29: (none) | F29: =COUNTIFS('Long Format'!$B$2:$B$642,A29,'Long Format'!$C$2:$C$642,B29,'Long Format'!$D$2:$D$642,"") -> 1
A30: Informed, engaged, and responsible community | D30: =SUMIFS('Long Format'!$E$2:$E$642,'Long Format'!$B$2:$B$642,A30) -> 140 | E30: =IF($D$1=0,0,D30/$D$1) -> 0.44164038 | F30: =COUNTIFS('Long Format'!$B$2:$B$642,A30) -> 191
A31: Informed, engaged, and responsible community | B31: Recreation | D31: =SUMIFS('Long Format'!$F$2:$F$642,'Long Format'!$B$2:$B$642,A31,'Long Format'!$C$2:$C$642,B31) -> 18 | E31: =IF($D$1=0,0,D31/$D$1) -> 0.056782334 | F31: =COUNTIFS('Long Format'!$B$2:$B$642,A31,'Long Format'!$C$2:$C$642,B31) -> 19 | I31: Recreation | J31: =D31 -> 18 | K31: =J31/$J$4*100 -> 12.857143
A32: Informed, engaged, and responsible community | B32: Recreation | C32: Availability | F32: =COUNTIFS('Long Format'!$B$2:$B$642,A32,'Long Format'!$C$2:$C$642,B32,'Long Format'!$D$2:$D$642,C32) -> 10 | I32: Availability | J32: =F32 -> 10 | K32: =J32/$J$4*100 -> 7.1428571
A33: Informed, engaged, and responsible community | B33: Recreation | C33: Accessibility | F33: =COUNTIFS('Long Format'!$B$2:$B$642,A33,'Long Format'!$C$2:$C$642,B33,'Long Format'!$D$2:$D$642,C33) -> 9 | I33: Accessibility | J33: =F33 -> 9 | K33: =J33/$J$4*100 -> 6.4285714
A34: Informed, engaged, and responsible community | B34: Recreation | C34: (none) | F34: =COUNTIFS('Long Format'!$B$2:$B$642,A34,'Long Format'!$C$2:$C$642,B34,'Long Format'!$D$2:$D$642,"") -> 0 | I34: Engagement | J34: =D45 -> 56 | K34: =J34/$J$4*100 -> 40
A35: Informed, engaged, and responsible community | B35: Well-being | D35: =SUMIFS('Long Format'!$F$2:$F$642,'Long Format'!$B$2:$B$642,A35,'Long Format'!$C$2:$C$642,B35) -> 17 | E35: =IF($D$1=0,0,D35/$D$1) -> 0.05362776 | F35: =COUNTIFS('Long Format'!$B$2:$B$642,A35,'Long Format'!$C$2:$C$642,B35) -> 17 | I35: Education | J35: =F46 -> 35 | K35: =J35/$J$4*100 -> 25
A36: Informed, engaged, and responsible community | B36: Well-being | C36: Safety | F36: =COUNTIFS('Long Format'!$B$2:$B$642,A36,'Long Format'!$C$2:$C$642,B36,'Long Format'!$D$2:$D$642,C36) -> 16 | I36: Involvement | J36: =F47 -> 29 | K36: =J36/$J$4*100 -> 20.714286
A37: Informed, engaged, and responsible community | B37: Well-being | C37: Mental health | F37: =COUNTIFS('Long Format'!$B$2:$B$642,A37,'Long Format'!$C$2:$C$642,B37,'Long Format'!$D$2:$D$642,C37) -> 1 | I37: Stewardship | J37: =D49 -> 20 | K37: =J37/$J$4*100 -> 14.285714
A38: Informed, engaged, and responsible community | B38: Well-being | C38: (none) | F38: =COUNTIFS('Long Format'!$B$2:$B$642,A38,'Long Format'!$C$2:$C$642,B38,'Long Format'!$D$2:$D$642,"") -> 0 | I38: Compliance | J38: =F50 -> 2 | K38: =J38/$J$4*100 -> 1.4285714
A39: Informed, engaged, and responsible community | B39: Governance | D39: =SUMIFS('Long Format'!$F$2:$F$642,'Long Format'!$B$2:$B$642,A39,'Long Format'!$C$2:$C$642,B39) -> 38 | E39: =IF($D$1=0,0,D39/$D$1) -> 0.11987382 | F39: =COUNTIFS('Long Format'!$B$2:$B$642,A39,'Long Format'!$C$2:$C$642,B39) -> 43 | I39: Accountability | J39: =F51 -> 18 | K39: =J39/$J$4*100 -> 12.857143
A40: Informed, engaged, and responsible community | B40: Governance | C40: Regulation | F40: =COUNTIFS('Long Format'!$B$2:$B$642,A40,'Long Format'!$C$2:$C$642,B40,'Long Format'!$D$2:$D$642,C40) -> 15 | I40: Governance | J40: =D39 -> 38 | K40: =J40/$J$4*100 -> 27.142857
A41: Informed, engaged, and responsible community | B41: Governance | C41: Enforcement | F41: =COUNTIFS('Long Format'!$B$2:$B$642,A41,'Long Format'!$C$2:$C$642,B41,'Long Format'!$D$2:$D$642,C41) -> 8 | I41: Regulation | J41: =F40 -> 15 | K41: =J41/$J$4*100 -> 10.714286
A42: Informed, engaged, and responsible community | B42: Governance | C42: Political influence | F42: =COUNTIFS('Long Format'!$B$2:$B$642,A42,'Long Format'!$C$2:$C$642,B42,'Long Format'!$D$2:$D$642,C42) -> 8 | I42: Enforcement | J42: =F41 -> 8 | K42: =J42/$J$4*100 -> 5.7142857
A43: Informed, engaged, and responsible community | B43: Governance | C43: Funding | F43: =COUNTIFS('Long Format'!$B$2:$B$642,A43,'Long Format'!$C$2:$C$642,B43,'Long Format'!$D$2:$D$642,C43) -> 9 | I43: Political influence | J43: =F42 -> 8 | K43: =J43/$J$4*100 -> 5.7142857
A44: Informed, engaged, and responsible community | B44: Governance | C44: (none) | F44: =COUNTIFS('Long Format'!$B$2:$B$642,A44,'Long Format'!$C$2:$C$642,B44,'Long Format'!$D$2:$D$642,"") -> 3 | I44: Funding | J44: =F43 -> 9 | K44: =J44/$J$4*100 -> 6.4285714
A45: Informed, engaged, and responsible community | B45: Engagement | D45: =SUMIFS('Long Format'!$F$2:$F$642,'Long Format'!$B$2:$B$642,A45,'Long Format'!$C$2:$C$642,B45) -> 56 | E45: =IF($D$1=0,0,D45/$D$1) -> 0.17665615 | F45: =COUNTIFS('Long Format'!$B$2:$B$642,A45,'Long Format'!$C$2:$C$642,B45) -> 64 | I45: Well-being | J45: =D35 -> 17 | K45: =J45/$J$4*100 -> 12.142857
A46: Informed, engaged, and responsible community | B46: Engagement | C46: Education | F46: =COUNTIFS('Long Format'!$B$2:$B$642,A46,'Long Format'!$C$2:$C$642,B46,'Long Format'!$D$2:$D$642,C46) -> 35 | I46: Safety | J46: =F36 -> 16 | K46: =J46/$J$4*100 -> 11.428571
A47: Informed, engaged, and responsible community | B47: Engagement | C47: Involvement | F47: =COUNTIFS('Long Format'!$B$2:$B$642,A47,'Long Format'!$C$2:$C$642,B47,'Long Format'!$D$2:$D$642,C47) -> 29 | I47: Mental health | J47: =F37 -> 1 | K47: =J47/$J$4*100 -> 0.71428571
A48: Informed, engaged, and responsible community | B48: Engagement | C48: (none) | F48: =COUNTIFS('Long Format'!$B$2:$B$642,A48,'Long Format'!$C$2:$C$642,B48,'Long Format'!$D$2:$D$642,"") -> 0 | I48: Climate change | J48: =D53 -> 28 | K48: =J48/$J$4*100 -> 20
A49: Informed, engaged, and responsible community | B49: Stewardship | D49: =SUMIFS('Long Format'!$F$2:$F$642,'Long Format'!$B$2:$B$642,A49,'Long Format'!$C$2:$C$642,B49) -> 20 | E49: =IF($D$1=0,0,D49/$D$1) -> 0.063091483 | F49: =COUNTIFS('Long Format'!$B$2:$B$642,A49,'Long Format'!$C$2:$C$642,B49) -> 20 | I49: Sustainability | J49: =F54 -> 5 | K49: =J49/$J$4*100 -> 3.5714286
A50: Informed, engaged, and responsible community | B50: Stewardship | C50: Compliance | F50: =COUNTIFS('Long Format'!$B$2:$B$642,A50,'Long Format'!$C$2:$C$642,B50,'Long Format'!$D$2:$D$642,C50) -> 2 | I50: Resilience | J50: =F55 -> 22 | K50: =J50/$J$4*100 -> 15.714286
A51: Informed, engaged, and responsible community | B51: Stewardship | C51: Accountability | F51: =COUNTIFS('Long Format'!$B$2:$B$642,A51,'Long Format'!$C$2:$C$642,B51,'Long Format'!$D$2:$D$642,C51) -> 18
A52: Informed, engaged, and responsible community | B52: Stewardship | C52: (none) | F52: =COUNTIFS('Long Format'!$B$2:$B$642,A52,'Long Format'!$C$2:$C$642,B52,'Long Format'!$D$2:$D$642,"") -> 0
A53: Informed, engaged, and responsible community | B53: Climate change | D53: =SUMIFS('Long Format'!$F$2:$F$642,'Long Format'!$B$2:$B$642,A53,'Long Format'!$C$2:$C$642,B53) -> 28 | E53: =IF($D$1=0,0,D53/$D$1) -> 0.088328076 | F53: =COUNTIFS('Long Format'!$B$2:$B$642,A53,'Long Format'!$C$2:$C$642,B53) -> 28
A54: Informed, engaged, and responsible community | B54: Climate change | C54: Sustainability | F54: =COUNTIFS('Long Format'!$B$2:$B$642,A54,'Long Format'!$C$2:$C$642,B54,'Long Format'!$D$2:$D$642,C54) -> 5
A55: Informed, engaged, and responsible community | B55: Climate change | C55: Resilience | F55: =COUNTIFS('Long Format'!$B$2:$B$642,A55,'Long Format'!$C$2:$C$642,B55,'Long Format'!$D$2:$D$642,C55) -> 22
A56: Informed, engaged, and responsible community | B56: Climate change | C56: (none) | F56: =COUNTIFS('Long Format'!$B$2:$B$642,A56,'Long Format'!$C$2:$C$642,B56,'Long Format'!$D$2:$D$642,"") -> 1
A57: Other | D57: =SUMIFS('Long Format'!$E$2:$E$642,'Long Format'!$B$2:$B$642,A57) -> 42 | E57: =IF($D$1=0,0,D57/$D$1) -> 0.13249211 | F57: =COUNTIFS('Long Format'!$B$2:$B$642,A57) -> 42
A58: Responses left uncoded | D58: =COUNTBLANK('Coded Responses'!F2:F335) -> 17
A59: Total code assignments | F59: =COUNTA('Long Format'!$B$2:$B$642) -> 641
